l2p/__init__.py
l2p/domain_builder.py
l2p/feedback_builder.py
l2p/prompt_builder.py
l2p/task_builder.py
l2p/llm/__init__.py
l2p/llm/base.py
l2p/llm/huggingface.py
l2p/llm/openai.py
l2p/llm/vllm.py
l2p/utils/__init__.py
l2p/utils/pddl_format.py
l2p/utils/pddl_parser.py
l2p/utils/pddl_planner.py
l2p/utils/pddl_types.py
l2p/utils/pddl_validator.py
l2p-0.3.0.dist-info/licenses/LICENSE
l2p-0.3.0.dist-info/METADATA
l2p-0.3.0.dist-info/WHEEL
l2p-0.3.0.dist-info/top_level.txt
l2p-0.3.0.dist-info/RECORD
