Metadata-Version: 2.4
Name: l2p
Version: 0.3.0
Summary: Library to connect LLMs and planning tasks
Home-page: https://github.com/AI-Planning/l2p
Author: Marcus Tantakoun, Christian Muise
Author-email: mtantakoun@gmail.com, christian.muise@gmail.com
License: MIT
Classifier: Programming Language :: Python :: 3
Classifier: License :: OSI Approved :: MIT License
Classifier: Operating System :: OS Independent
Requires-Python: >=3.10
License-File: LICENSE
Requires-Dist: retry
Requires-Dist: pddl
Requires-Dist: typing_extensions
Dynamic: author
Dynamic: author-email
Dynamic: classifier
Dynamic: description
Dynamic: description-content-type
Dynamic: home-page
Dynamic: license
Dynamic: license-file
Dynamic: requires-dist
Dynamic: requires-python
Dynamic: summary
